setup.py
marcosz_distributions/Binomialdistribution.py
marcosz_distributions/Gaussiandistribution.py
marcosz_distributions/Generaldistribution.py
marcosz_distributions/__init__.py
marcosz_distributions.egg-info/PKG-INFO
marcosz_distributions.egg-info/SOURCES.txt
marcosz_distributions.egg-info/dependency_links.txt
marcosz_distributions.egg-info/not-zip-safe
marcosz_distributions.egg-info/top_level.txt